main.py
mseep_mcpexample-0.1.3.dist-info/METADATA
mseep_mcpexample-0.1.3.dist-info/WHEEL
mseep_mcpexample-0.1.3.dist-info/entry_points.txt
mseep_mcpexample-0.1.3.dist-info/top_level.txt
mseep_mcpexample-0.1.3.dist-info/RECORD
