Metadata-Version: 2.4
Name: mseep-mcpexample
Version: 0.1.3
Summary: Add your description here
Author-email: mseep <support@skydeck.ai>
Requires-Python: >=3.10
Requires-Dist: httpx>=0.28.1
Requires-Dist: mcp[cli]>=1.4.1
Requires-Dist: mythic>=0.2.5
